{
  "one": {
  "number": 1,
  "numberAudio": "one.ogg",
  "order": 1
    },
  "two": {
    "number": 2,
    "numberAudio": "2.ogg",
    "order": 2
  },
   "three": {
     "number": 3,
    "numberAudio": "3.ogg",
    "order": 3
  },
  "four": {
    "number": 4,
    "numberAudio": "4.ogg",
    "order": 4
  },
  "five": {
    "number": 5,
   "numberAudio": "5.ogg",
   "order": 5
  },
  "six": {
    "number": 6,
    "numberAudio": "6.ogg",
    "order": 6
  },
  "seven": {
    "number": 7,
    "numberAudio": "7.ogg",
    "order": 7
  },
  "eight": {
    "number": 8,
    "numberAudio": "8.ogg",
    "order": 8
},
"nine": {
  "number": 9,
  "numberAudio": "9.ogg",
  "order": 9
},
"ten": {
  "number": 10,
  "numberAudio": "10.ogg",
  "order": 10
},
"eleven": {
  "number": 11,
  "numberAudio": "11.ogg",
  "order": 11
},
"twelve": {
  "number": 12,
  "numberAudio": "12.ogg",
  "order": 12
},
"thirteen": {
  "number": 13,
  "numberAudio": "andi.mp3",
  "order": 13
},
"fourteen": {
  "number": 14,
  "numberAudio": "andi.mp3",
  "order": 14
},
"fifteen": {
  "number": 15,
  "numberAudio": "andi.mp3",
  "order": 15
},
"sixteen": {
  "number": 16,
  "numberAudio": "andi.mp3",
  "order": 16
},
"seventeen": {
  "number": 17,
  "numberAudio": "andi.mp3",
  "order": 17
},
"eighteen": {
  "number": 18,
  "numberAudio": "andi.mp3",
  "order": 18
},
"nineteen": {
  "number": 19,
  "numberAudio": "andi.mp3",
  "order": 19
},
"twenty": {
  "number": 20,
  "numberAudio": "andi.mp3",
  "order": 20
}
}